iocbio/fcs/app/__init__.py
iocbio/fcs/app/calc_acf.py
iocbio/fcs/app/calc_dcn.py
iocbio/fcs/app/calc_psf_values.py
iocbio/fcs/app/fit.py
iocbio/fcs/app/fit_bayes.py
iocbio/fcs/app/fit_psf.py
iocbio/fcs/app/plot.py
iocbio/fcs/lib/__init__.py
iocbio/fcs/lib/acf.py
iocbio/fcs/lib/base_model.py
iocbio/fcs/lib/const.py
iocbio/fcs/lib/filter_acquisition_attributes.py
iocbio/fcs/lib/fit.py
iocbio/fcs/lib/input.py
iocbio/fcs/lib/map.py
iocbio/fcs/lib/plot.py
iocbio/fcs/lib/plot_acf_vs_angle.py
iocbio/fcs/lib/plot_bayes.py
iocbio/fcs/lib/plot_cov.py
iocbio/fcs/lib/plot_dcn.py
iocbio/fcs/lib/plot_signal.py
iocbio/fcs/lib/psf.py
iocbio/fcs/lib/residual.py
iocbio/fcs/lib/result.py
iocbio/fcs/lib/utils.py
iocbio/fcs/lib/engines/prodtools.cp311-win_amd64.pyd
iocbio/fcs/lib/engines/prodtools.cpp
iocbio/fcs/lib/engines/prodtools_impl.cpp
iocbio/fcs/lib/engines/psfmult.cp311-win_amd64.pyd
iocbio/fcs/lib/engines/psfmult.cpp
iocbio/fcs/lib/engines/psfmult_impl.cpp
iocbio/fcs/models/analytical_acf.py
iocbio/fcs/models/analytical/__init__.py
iocbio/fcs/models/analytical/analytical_psf.py
iocbio/fcs/models/analytical/diff3D.py
iocbio/fcs/models/analytical/diff3D_2comp.py
iocbio/fcs/models/analytical/diff3D_2comp_triplet.py
iocbio/fcs/models/analytical/diff3D_triplet.py
iocbio/fcs/models/psf/diff3D_2comp_psf.py
iocbio/fcs/models/psf/diff3D_2comp_triplet_psf.py
iocbio/fcs/models/psf/diff3D_psf.py
iocbio/fcs/models/psf/diff3D_triplet_psf.py
iocbio/fcs/models/psf/experimental_psf.py
iocbio_fcs-1.1.0.dist-info/licenses/AUTHORS.md
iocbio_fcs-1.1.0.dist-info/licenses/LICENSE.md
iocbio_fcs-1.1.0.dist-info/METADATA
iocbio_fcs-1.1.0.dist-info/WHEEL
iocbio_fcs-1.1.0.dist-info/entry_points.txt
iocbio_fcs-1.1.0.dist-info/top_level.txt
iocbio_fcs-1.1.0.dist-info/RECORD
