Metadata-Version: 2.4
Name: iocbio.fcs
Version: 1.1.0
Summary: ACF Calculation from Experimental Data, Plotting and Fitting Used by FCS and RICS Methods
Author-email: IOCBio team <iocbio@sysbio.ioc.ee>
License: GPLv3
Project-URL: Homepage, https://iocbio.gitlab.io/fcs/
Keywords: FCS,RICS,fluorescence,correlation,spectroscopy,microscopy,autocorrelation
Classifier: Development Status :: 4 - Beta
Classifier: Intended Audience :: Science/Research
Classifier: Topic :: Scientific/Engineering :: Bio-Informatics
Classifier: Topic :: Scientific/Engineering :: Physics
Classifier: Topic :: Scientific/Engineering :: Image Processing
Classifier: License :: OSI Approved :: GNU General Public License v3 or later (GPLv3+)
Classifier: Programming Language :: Python :: 3
Classifier: Programming Language :: Cython
Requires-Python: >=3.11
License-File: LICENSE.md
License-File: AUTHORS.md
Requires-Dist: arviz
Requires-Dist: scipy
Requires-Dist: numpy
Requires-Dist: h5py
Requires-Dist: matplotlib
Requires-Dist: ultranest
Requires-Dist: xlwt
Requires-Dist: cython
Requires-Dist: pyqtgraph
Requires-Dist: PySide6
Dynamic: license-file
